LICENSE
README.md
setup.py
anvolt/__init__.py
anvolt/cli.py
anvolt/request.py
anvolt/updater.py
anvolt/utils.py
anvolt.py.egg-info/PKG-INFO
anvolt.py.egg-info/SOURCES.txt
anvolt.py.egg-info/dependency_links.txt
anvolt.py.egg-info/entry_points.txt
anvolt.py.egg-info/requires.txt
anvolt.py.egg-info/top_level.txt
anvolt/api/__init__.py
anvolt/api/games.py
anvolt/api/nsfw.py
anvolt/api/sfw.py
anvolt/models/__init__.py
anvolt/models/enums.py
anvolt/models/errors.py
anvolt/models/response.py
anvolt/notifier/__init__.py
anvolt/notifier/notification.py
anvolt/notifier/twitch.py
anvolt/trivia/__init__.py
anvolt/trivia/trivia.py