Metadata-Version: 2.1
Name: anvolt.py
Version: 0.1.6
Summary: Advanced tool with API integration and additional features
Home-page: https://anvolt.vercel.app/api/
Author: Stawa
License: MIT
Project-URL: Source, https://github.com/Stawa/anvolt.py
Project-URL: Tracker, https://github.com/Stawa/anvolt.py/issues
Project-URL: Changelog, https://github.com/Stawa/anvolt.py/blob/main/CHANGELOG.md
Keywords: api,anime,games,roleplay,images,trivia,discord,webhooks,twitch
Classifier: Development Status :: 2 - Pre-Alpha
Classifier: Programming Language :: Python :: 3.9
Classifier: Programming Language :: Python :: 3.10
Classifier: License :: OSI Approved :: MIT License
Classifier: Natural Language :: English
Classifier: Typing :: Typed
Classifier: Intended Audience :: Developers
Classifier: Operating System :: OS Independent
Classifier: Environment :: Console
Provides-Extra: cli
License-File: LICENSE
